flask_menu/__init__.py
flask_menu/ext.py
flask_menu/menu.py
flask_menu/proxies.py
flask_menu-2.0.0.dist-info/AUTHORS.rst
flask_menu-2.0.0.dist-info/LICENSE
flask_menu-2.0.0.dist-info/METADATA
flask_menu-2.0.0.dist-info/WHEEL
flask_menu-2.0.0.dist-info/top_level.txt
flask_menu-2.0.0.dist-info/RECORD
