Metadata-Version: 2.1
Name: flask-menu
Version: 2.0.0
Summary: "Flask-Menu is a Flask extension that adds support for generating menus."
Home-page: https://github.com/inveniosoftware/flask-menu
Author: Invenio collaboration
Author-email: info@inveniosoftware.org
License: BSD
Platform: any
Classifier: Development Status :: 5 - Production/Stable
Requires-Python: >=3.7
License-File: LICENSE
License-File: AUTHORS.rst
Requires-Dist: Flask>=2.0.0
Provides-Extra: tests
Requires-Dist: check-manifest>=0.49; extra == "tests"
Requires-Dist: pytest-black-ng>=0.3.0; extra == "tests"
Requires-Dist: pytest-cov>=4.1.0; extra == "tests"
Requires-Dist: pytest-flask>=1.2.0; extra == "tests"
Requires-Dist: pytest-isort>=3.1.0; extra == "tests"
Requires-Dist: pytest-pydocstyle>=2.3.2; extra == "tests"
Requires-Dist: sphinx>=4.5; extra == "tests"
